easymodelskeras/__init__.py
singularitytechnologies.easymodelskeras-0.1.17.dev0.dist-info/LICENSE
singularitytechnologies.easymodelskeras-0.1.17.dev0.dist-info/METADATA
singularitytechnologies.easymodelskeras-0.1.17.dev0.dist-info/WHEEL
singularitytechnologies.easymodelskeras-0.1.17.dev0.dist-info/top_level.txt
singularitytechnologies.easymodelskeras-0.1.17.dev0.dist-info/RECORD
