Metadata-Version: 2.1
Name: singularitytechnologies.easymodelskeras
Version: 0.1.17.dev0
Summary: Easy to use Keras Machine Learning Model 
Home-page: https://github.com/singularitydigitaltechnologies/easymodelskeras
Author: Sam Lacey
Author-email: sam.lacey@singularity-technologies.io
License: UNKNOWN
Platform: UNKNOWN
Classifier: Programming Language :: Python :: 3
Classifier: License :: OSI Approved :: GNU General Public License v3 (GPLv3)
Classifier: Operating System :: OS Independent
Requires-Dist: absl-py (==0.7.0)
Requires-Dist: astor (==0.7.1)
Requires-Dist: backcall (==0.1.0)
Requires-Dist: decorator (==4.3.2)
Requires-Dist: gast (==0.2.2)
Requires-Dist: grpcio (==1.19.0)
Requires-Dist: h5py (==2.9.0)
Requires-Dist: jedi (==0.13.3)
Requires-Dist: Keras (==2.2.4)
Requires-Dist: Keras-Applications (==1.0.7)
Requires-Dist: Keras-Preprocessing (==1.0.9)
Requires-Dist: Markdown (==3.0.1)
Requires-Dist: numpy (==1.16.2)
Requires-Dist: parso (==0.3.4)
Requires-Dist: pexpect (==4.6.0)
Requires-Dist: pickleshare (==0.7.5)
Requires-Dist: prompt-toolkit (==2.0.9)
Requires-Dist: protobuf (==3.7.0)
Requires-Dist: ptyprocess (==0.6.0)
Requires-Dist: Pygments (==2.3.1)
Requires-Dist: PyYAML (==4.2b1)
Requires-Dist: scipy (==1.2.1)
Requires-Dist: singularitytechnologies.easymodels (==0.1.13dev)
Requires-Dist: six (==1.12.0)
Requires-Dist: tensorboard (==1.12.2)
Requires-Dist: tensorflow (==1.12.0)
Requires-Dist: termcolor (==1.1.0)
Requires-Dist: traitlets (==4.3.2)
Requires-Dist: wcwidth (==0.1.7)
Requires-Dist: Werkzeug (==0.14.1)
